lymo/__init__.py
lymo/db.py
lymo/dsql.py
lymo/http_handler.py
lymo/http_requests.py
lymo/http_responses.py
lymo/router.py
lymo/serializer.py
lymo/templating.py
lymo-0.11.dist-info/licenses/LICENSE
lymo-0.11.dist-info/METADATA
lymo-0.11.dist-info/WHEEL
lymo-0.11.dist-info/top_level.txt
lymo-0.11.dist-info/RECORD
