Metadata-Version: 2.4
Name: lymo
Version: 0.11
Summary: Python HTTP micro-framework for AWS Lambda.
Home-page: https://github.com/newadventures/lymo
Author: New Adventures In Coding
Author-email: mail@neiladventures.dev
Maintainer: New Adventures In Coding
Maintainer-email: mail@neiladventures.dev
License: BSD-3-Clause
Classifier: Development Status :: 3 - Alpha
Classifier: Intended Audience :: Developers
Classifier: License :: OSI Approved :: BSD License
Classifier: Natural Language :: English
Classifier: Operating System :: OS Independent
Classifier: Programming Language :: Python :: 3
Classifier: Programming Language :: Python :: 3 :: Only
Classifier: Programming Language :: Python :: 3.10
Classifier: Programming Language :: Python :: 3.11
Classifier: Programming Language :: Python :: 3.12
Classifier: Programming Language :: Python :: 3.13
Classifier: Programming Language :: Python :: Implementation :: CPython
Requires-Python: >=3.10
License-File: LICENSE
Provides-Extra: db
Requires-Dist: pydantic~=2.12.0; extra == "db"
Requires-Dist: psycopg[binary]~=3.2.0; extra == "db"
Provides-Extra: templates
Requires-Dist: Jinja2~=3.1.0; extra == "templates"
Provides-Extra: dev
Requires-Dist: ruff; extra == "dev"
Requires-Dist: twine; extra == "dev"
Requires-Dist: tblib; extra == "dev"
Requires-Dist: ipython; extra == "dev"
Requires-Dist: python-dotenv; extra == "dev"
Requires-Dist: boto3; extra == "dev"
Requires-Dist: boto3-stubs[full]; extra == "dev"
Requires-Dist: aws-lambda-typing; extra == "dev"
Dynamic: license-file
